get_chrome_driver/__init__.py
get_chrome_driver/app.py
get_chrome_driver/constants.py
get_chrome_driver/downloader.py
get_chrome_driver/exceptions.py
get_chrome_driver/get_driver.py
get_chrome_driver/enums/__init__.py
get_chrome_driver/enums/os_platform.py
get_chrome_driver/enums/phase.py
get_chrome_driver/enums/platform.py
get_chrome_driver-1.5.1.dist-info/licenses/LICENSE
tests/__init__.py
tests/test_app.py
get_chrome_driver-1.5.1.dist-info/METADATA
get_chrome_driver-1.5.1.dist-info/WHEEL
get_chrome_driver-1.5.1.dist-info/entry_points.txt
get_chrome_driver-1.5.1.dist-info/top_level.txt
get_chrome_driver-1.5.1.dist-info/RECORD
