Metadata-Version: 2.4
Name: get-chrome-driver
Version: 1.5.1
Summary: A tool to download and install ChromeDriver.
Home-page: https://github.com/zaironjacobs/get-chrome-driver
Download-URL: https://github.com/zaironjacobs/get-chrome-driver/archive/v1.5.1.tar.gz
Author: Zairon Jacobs
Author-email: zaironjacobs@gmail.com
License: MIT
Keywords: chrome,chromedriver,download,install,web,driver,tool
Classifier: Development Status :: 5 - Production/Stable
Classifier: Intended Audience :: Developers
Classifier: License :: OSI Approved :: MIT License
Classifier: Operating System :: OS Independent
Classifier: Programming Language :: Python :: 3.11
Classifier: Natural Language :: English
Requires-Python: >=3
License-File: LICENSE
Requires-Dist: beautifulsoup4==4.13.5
Requires-Dist: requests==2.32.5
Requires-Dist: urllib3==2.5.0
Requires-Dist: typer==0.17.4
Dynamic: author
Dynamic: author-email
Dynamic: classifier
Dynamic: description
Dynamic: download-url
Dynamic: home-page
Dynamic: keywords
Dynamic: license
Dynamic: license-file
Dynamic: requires-dist
Dynamic: requires-python
Dynamic: summary
